[
  {
    "name": "Ethereum",
    "symbol": "ETH",
    "gas_symbol": "ETH",
    "gov_symbol": "ETH",
    "category": "L1",
    "is_testnet": false,
    "price": 1978.8,
    "change": -5.60509,
    "fdv": 238822380681,
    "mcap": 238822380681,
    "tvl": 58000000000,
    "tx": 878603,
    "fees": 10383.150790567763,
    "float": 1.0
  },
  {
    "name": "Arbitrum",
    "symbol": "ARB",
    "gas_symbol": "ETH",
    "gov_symbol": "ARB",
    "category": "L2",
    "is_testnet": false,
    "price": 0.09985,
    "change": -3.96171,
    "fdv": 998505679,
    "mcap": 593020007,
    "tvl": 16000000000,
    "tx": 1186157,
    "fees": 12403.96754084487,
    "float": 0.5939074954424971
  },
  {
    "name": "Solana",
    "symbol": "SOL",
    "gas_symbol": "SOL",
    "gov_symbol": "SOL",
    "category": "L1",
    "is_testnet": false,
    "price": 84.86,
    "change": -5.16496,
    "fdv": 52782230246,
    "mcap": 48384995412,
    "tvl": 6500000000,
    "tx": 33157994,
    "fees": 1208295.9349780777,
    "float": 0.9166909997264991
  },
  {
    "name": "Base",
    "symbol": "ETH",
    "gas_symbol": "ETH",
    "gov_symbol": null,
    "category": "L2",
    "is_testnet": false,
    "price": 1.36e-06,
    "change": -4.53622,
    "fdv": 1110424,
    "mcap": 0.0,
    "tvl": 2500000000,
    "tx": 1037204,
    "fees": 13910.118828373452,
    "float": 0.0
  },
  {
    "name": "Sui",
    "symbol": "SUI",
    "gas_symbol": "SUI",
    "gov_symbol": "SUI",
    "category": "L1",
    "is_testnet": false,
    "price": 0.900529,
    "change": -6.53471,
    "fdv": 9006211483,
    "mcap": 3512408688,
    "tvl": 1200000000,
    "tx": 1199983,
    "fees": 42797.92664742467,
    "float": 0.3899984687934515
  },
  {
    "name": "Hyperliquid",
    "symbol": "HYPE",
    "gas_symbol": "USDC",
    "gov_symbol": "HYPE",
    "category": "L1",
    "is_testnet": false,
    "price": 138.0,
    "change": 0.04,
    "fdv": 13800000000,
    "mcap": 4500000000,
    "tvl": 900000000,
    "tx": 926600,
    "fees": 16366.430659114236,
    "float": 0.32608695652173914
  },
  {
    "name": "Monad",
    "symbol": "MON",
    "gas_symbol": "MON",
    "gov_symbol": "MON",
    "category": "L1",
    "is_testnet": false,
    "price": 18.5,
    "change": -0.46,
    "fdv": 18500000000,
    "mcap": 2700000000,
    "tvl": 850000000,
    "tx": 39763325,
    "fees": 1337401.713957054,
    "float": 0.14594594594594595
  },
  {
    "name": "Aptos",
    "symbol": "APT",
    "gas_symbol": "APT",
    "gov_symbol": "APT",
    "category": "L1",
    "is_testnet": false,
    "price": 0.952943,
    "change": -5.20542,
    "fdv": 1142372502,
    "mcap": 744329877,
    "tvl": 550000000,
    "tx": 1132753,
    "fees": 33392.63726344738,
    "float": 0.6515649454944601
  },
  {
    "name": "Berachain",
    "symbol": "BERA",
    "gas_symbol": "BERA",
    "gov_symbol": "BGT",
    "category": "L1",
    "is_testnet": true,
    "price": 0,
    "change": 0,
    "fdv": 2500000000,
    "mcap": 0,
    "tvl": 450000000,
    "tx": 1008048,
    "fees": 28002.716867397303,
    "float": 0.0
  },
  {
    "name": "Sei",
    "symbol": "SEI",
    "gas_symbol": "SEI",
    "gov_symbol": "SEI",
    "category": "L1",
    "is_testnet": false,
    "price": 0.066196,
    "change": -2.72696,
    "fdv": 661949411,
    "mcap": 445712603,
    "tvl": 220000000,
    "tx": 1035461,
    "fees": 31118.08229169264,
    "float": 0.6733333327189863
  }
]