[
  {
    "name": "Ethereum",
    "symbol": "ETH",
    "gas_symbol": "ETH",
    "gov_symbol": "ETH",
    "category": "L1",
    "is_testnet": false,
    "price": 2977.84,
    "change": 0.51332,
    "fdv": 359547489158,
    "mcap": 359547489158,
    "tvl": 58000000000,
    "tx": 1080966,
    "fees": 22252.65095255076,
    "float": 1.0
  },
  {
    "name": "Arbitrum",
    "symbol": "ARB",
    "gas_symbol": "ETH",
    "gov_symbol": "ARB",
    "category": "L2",
    "is_testnet": false,
    "price": 0.194911,
    "change": 4.44923,
    "fdv": 1949487479,
    "mcap": 1114967717,
    "tvl": 16000000000,
    "tx": 915724,
    "fees": 7033.360247495855,
    "float": 0.5719286371471997
  },
  {
    "name": "Solana",
    "symbol": "SOL",
    "gas_symbol": "SOL",
    "gov_symbol": "SOL",
    "category": "L1",
    "is_testnet": false,
    "price": 124.42,
    "change": -0.16488,
    "fdv": 76846332445,
    "mcap": 70093596262,
    "tvl": 6500000000,
    "tx": 35781888,
    "fees": 1755364.2148522455,
    "float": 0.9121267604041737
  },
  {
    "name": "Base",
    "symbol": "ETH",
    "gas_symbol": "ETH",
    "gov_symbol": null,
    "category": "L2",
    "is_testnet": false,
    "price": 2.3e-06,
    "change": -2.76081,
    "fdv": 1879311,
    "mcap": 0.0,
    "tvl": 2500000000,
    "tx": 953172,
    "fees": 36715.81476021342,
    "float": 0.0
  },
  {
    "name": "Sui",
    "symbol": "SUI",
    "gas_symbol": "SUI",
    "gov_symbol": "SUI",
    "category": "L1",
    "is_testnet": false,
    "price": 1.43,
    "change": 1.6493,
    "fdv": 14302235373,
    "mcap": 5423669491,
    "tvl": 1200000000,
    "tx": 1023288,
    "fees": 27628.2379810388,
    "float": 0.3792183074569514
  },
  {
    "name": "Hyperliquid",
    "symbol": "HYPE",
    "gas_symbol": "USDC",
    "gov_symbol": "HYPE",
    "category": "L1",
    "is_testnet": false,
    "price": 138.0,
    "change": 0.53,
    "fdv": 13800000000,
    "mcap": 4500000000,
    "tvl": 900000000,
    "tx": 802244,
    "fees": 18330.0209054488,
    "float": 0.32608695652173914
  },
  {
    "name": "Monad",
    "symbol": "MON",
    "gas_symbol": "MON",
    "gov_symbol": "MON",
    "category": "L1",
    "is_testnet": false,
    "price": 18.5,
    "change": -0.98,
    "fdv": 18500000000,
    "mcap": 2700000000,
    "tvl": 850000000,
    "tx": 45902700,
    "fees": 1890318.082128576,
    "float": 0.14594594594594595
  },
  {
    "name": "Aptos",
    "symbol": "APT",
    "gas_symbol": "APT",
    "gov_symbol": "APT",
    "category": "L1",
    "is_testnet": false,
    "price": 1.79,
    "change": 7.06319,
    "fdv": 2129031456,
    "mcap": 1341961111,
    "tvl": 550000000,
    "tx": 830547,
    "fees": 21049.84038402842,
    "float": 0.6303153047448445
  },
  {
    "name": "Berachain",
    "symbol": "BERA",
    "gas_symbol": "BERA",
    "gov_symbol": "BGT",
    "category": "L1",
    "is_testnet": true,
    "price": 0,
    "change": 0,
    "fdv": 2500000000,
    "mcap": 0,
    "tvl": 450000000,
    "tx": 994599,
    "fees": 5487.593842303991,
    "float": 0.0
  },
  {
    "name": "Sei",
    "symbol": "SEI",
    "gas_symbol": "SEI",
    "gov_symbol": "SEI",
    "category": "L1",
    "is_testnet": false,
    "price": 0.114413,
    "change": 2.89851,
    "fdv": 1144769806,
    "mcap": 743082801,
    "tvl": 220000000,
    "tx": 897465,
    "fees": 33498.67444707337,
    "float": 0.6491111113390075
  }
]