[
  {
    "name": "Ethereum",
    "symbol": "ETH",
    "gas_symbol": "ETH",
    "gov_symbol": "ETH",
    "category": "L1",
    "is_testnet": false,
    "price": 3118.74,
    "change": -2.71498,
    "fdv": 376236997368,
    "mcap": 376236997368,
    "tvl": 58000000000,
    "tx": 1019933,
    "fees": 42043.269357591045,
    "float": 1.0
  },
  {
    "name": "Arbitrum",
    "symbol": "ARB",
    "gas_symbol": "ETH",
    "gov_symbol": "ARB",
    "category": "L2",
    "is_testnet": false,
    "price": 0.210188,
    "change": -1.21664,
    "fdv": 2099801878,
    "mcap": 1179699947,
    "tvl": 16000000000,
    "tx": 897541,
    "fees": 34871.38982548026,
    "float": 0.5618148832801454
  },
  {
    "name": "Solana",
    "symbol": "SOL",
    "gas_symbol": "SOL",
    "gov_symbol": "SOL",
    "category": "L1",
    "is_testnet": false,
    "price": 133.43,
    "change": -2.93347,
    "fdv": 82200543658,
    "mcap": 74976915416,
    "tvl": 6500000000,
    "tx": 26351024,
    "fees": 830406.9832249469,
    "float": 0.9121218921366955
  },
  {
    "name": "Base",
    "symbol": "ETH",
    "gas_symbol": "ETH",
    "gov_symbol": null,
    "category": "L2",
    "is_testnet": false,
    "price": 2.24e-06,
    "change": 1.33717,
    "fdv": 1822657,
    "mcap": 0.0,
    "tvl": 2500000000,
    "tx": 1170126,
    "fees": 12583.363890898181,
    "float": 0.0
  },
  {
    "name": "Sui",
    "symbol": "SUI",
    "gas_symbol": "SUI",
    "gov_symbol": "SUI",
    "category": "L1",
    "is_testnet": false,
    "price": 1.61,
    "change": -1.52638,
    "fdv": 16049029273,
    "mcap": 5997307761,
    "tvl": 1200000000,
    "tx": 824776,
    "fees": 32104.90541398327,
    "float": 0.3736866360565208
  },
  {
    "name": "Hyperliquid",
    "symbol": "HYPE",
    "gas_symbol": "USDC",
    "gov_symbol": "HYPE",
    "category": "L1",
    "is_testnet": false,
    "price": 138.0,
    "change": -0.7,
    "fdv": 13800000000,
    "mcap": 4500000000,
    "tvl": 900000000,
    "tx": 999461,
    "fees": 8759.010703408265,
    "float": 0.32608695652173914
  },
  {
    "name": "Monad",
    "symbol": "MON",
    "gas_symbol": "MON",
    "gov_symbol": "MON",
    "category": "L1",
    "is_testnet": false,
    "price": 18.5,
    "change": 0.87,
    "fdv": 18500000000,
    "mcap": 2700000000,
    "tvl": 850000000,
    "tx": 42509375,
    "fees": 1181477.6426386621,
    "float": 0.14594594594594595
  },
  {
    "name": "Aptos",
    "symbol": "APT",
    "gas_symbol": "APT",
    "gov_symbol": "APT",
    "category": "L1",
    "is_testnet": false,
    "price": 1.67,
    "change": -0.15116,
    "fdv": 1975084801,
    "mcap": 1243421813,
    "tvl": 550000000,
    "tx": 908580,
    "fees": 7828.141098431284,
    "float": 0.6295536335302901
  },
  {
    "name": "Berachain",
    "symbol": "BERA",
    "gas_symbol": "BERA",
    "gov_symbol": "BGT",
    "category": "L1",
    "is_testnet": true,
    "price": 0,
    "change": 0,
    "fdv": 2500000000,
    "mcap": 0,
    "tvl": 450000000,
    "tx": 897461,
    "fees": 18653.036142364967,
    "float": 0.0
  },
  {
    "name": "Sei",
    "symbol": "SEI",
    "gas_symbol": "SEI",
    "gov_symbol": "SEI",
    "category": "L1",
    "is_testnet": false,
    "price": 0.128864,
    "change": -2.58801,
    "fdv": 1286394321,
    "mcap": 819433183,
    "tvl": 220000000,
    "tx": 1040870,
    "fees": 4439.883357005111,
    "float": 0.6370000004065628
  }
]