[
  {
    "name": "Ethereum",
    "symbol": "ETH",
    "gas_symbol": "ETH",
    "gov_symbol": "ETH",
    "category": "L1",
    "is_testnet": false,
    "price": 2693.5,
    "change": -1.34434,
    "fdv": 325086622897,
    "mcap": 325086622897,
    "tvl": 58000000000,
    "tx": 1127535,
    "fees": 19570.578015385458,
    "float": 1.0
  },
  {
    "name": "Arbitrum",
    "symbol": "ARB",
    "gas_symbol": "ETH",
    "gov_symbol": "ARB",
    "category": "L2",
    "is_testnet": false,
    "price": 0.153649,
    "change": 0.11625,
    "fdv": 1536923064,
    "mcap": 895532033,
    "tvl": 16000000000,
    "tx": 1051761,
    "fees": 31510.171360756813,
    "float": 0.5826785048493488
  },
  {
    "name": "Solana",
    "symbol": "SOL",
    "gas_symbol": "SOL",
    "gov_symbol": "SOL",
    "category": "L1",
    "is_testnet": false,
    "price": 118.46,
    "change": 3.33809,
    "fdv": 73380220789,
    "mcap": 67085349428,
    "tvl": 6500000000,
    "tx": 27832051,
    "fees": 1210574.4084463315,
    "float": 0.914215693366466
  },
  {
    "name": "Base",
    "symbol": "ETH",
    "gas_symbol": "ETH",
    "gov_symbol": null,
    "category": "L2",
    "is_testnet": false,
    "price": 1.65e-06,
    "change": 3.54691,
    "fdv": 1343450,
    "mcap": 0.0,
    "tvl": 2500000000,
    "tx": 1040549,
    "fees": 18102.444987566156,
    "float": 0.0
  },
  {
    "name": "Sui",
    "symbol": "SUI",
    "gas_symbol": "SUI",
    "gov_symbol": "SUI",
    "category": "L1",
    "is_testnet": false,
    "price": 1.25,
    "change": -2.77332,
    "fdv": 12490184155,
    "mcap": 4736506495,
    "tvl": 1200000000,
    "tx": 1190951,
    "fees": 34693.99008065966,
    "float": 0.37921830745016744
  },
  {
    "name": "Hyperliquid",
    "symbol": "HYPE",
    "gas_symbol": "USDC",
    "gov_symbol": "HYPE",
    "category": "L1",
    "is_testnet": false,
    "price": 138.0,
    "change": 1.2,
    "fdv": 13800000000,
    "mcap": 4500000000,
    "tvl": 900000000,
    "tx": 883421,
    "fees": 27355.551769668888,
    "float": 0.32608695652173914
  },
  {
    "name": "Monad",
    "symbol": "MON",
    "gas_symbol": "MON",
    "gov_symbol": "MON",
    "category": "L1",
    "is_testnet": false,
    "price": 18.5,
    "change": -0.92,
    "fdv": 18500000000,
    "mcap": 2700000000,
    "tvl": 850000000,
    "tx": 35185797,
    "fees": 768391.5600279823,
    "float": 0.14594594594594595
  },
  {
    "name": "Aptos",
    "symbol": "APT",
    "gas_symbol": "APT",
    "gov_symbol": "APT",
    "category": "L1",
    "is_testnet": false,
    "price": 1.43,
    "change": -1.27808,
    "fdv": 1707857345,
    "mcap": 1094572437,
    "tvl": 550000000,
    "tx": 825491,
    "fees": 18840.813772082263,
    "float": 0.6409039023104123
  },
  {
    "name": "Berachain",
    "symbol": "BERA",
    "gas_symbol": "BERA",
    "gov_symbol": "BGT",
    "category": "L1",
    "is_testnet": true,
    "price": 0,
    "change": 0,
    "fdv": 2500000000,
    "mcap": 0,
    "tvl": 450000000,
    "tx": 1156317,
    "fees": 26470.888237503554,
    "float": 0.0
  },
  {
    "name": "Sei",
    "symbol": "SEI",
    "gas_symbol": "SEI",
    "gov_symbol": "SEI",
    "category": "L1",
    "is_testnet": false,
    "price": 0.094589,
    "change": -0.56036,
    "fdv": 946495272,
    "mcap": 625843707,
    "tvl": 220000000,
    "tx": 1157067,
    "fees": 48415.987077641366,
    "float": 0.6612222221433347
  }
]