[
  {
    "name": "Ethereum",
    "symbol": "ETH",
    "gas_symbol": "ETH",
    "gov_symbol": "ETH",
    "category": "L1",
    "is_testnet": false,
    "price": 2958.43,
    "change": 0.63368,
    "fdv": 356843659556,
    "mcap": 356843659556,
    "tvl": 58000000000,
    "tx": 1105785,
    "fees": 45229.5267279577,
    "float": 1.0
  },
  {
    "name": "Arbitrum",
    "symbol": "ARB",
    "gas_symbol": "ETH",
    "gov_symbol": "ARB",
    "category": "L2",
    "is_testnet": false,
    "price": 0.19062,
    "change": 1.08086,
    "fdv": 1905371177,
    "mcap": 1089736341,
    "tvl": 16000000000,
    "tx": 1067951,
    "fees": 22207.164088908317,
    "float": 0.5719286373985073
  },
  {
    "name": "Solana",
    "symbol": "SOL",
    "gas_symbol": "SOL",
    "gov_symbol": "SOL",
    "category": "L1",
    "is_testnet": false,
    "price": 124.06,
    "change": 1.008,
    "fdv": 76516523999,
    "mcap": 69778154780,
    "tvl": 6500000000,
    "tx": 28112807,
    "fees": 876398.275614409,
    "float": 0.9119357641090954
  },
  {
    "name": "Base",
    "symbol": "ETH",
    "gas_symbol": "ETH",
    "gov_symbol": null,
    "category": "L2",
    "is_testnet": false,
    "price": 2.37e-06,
    "change": -2.78666,
    "fdv": 1934921,
    "mcap": 0.0,
    "tvl": 2500000000,
    "tx": 1188406,
    "fees": 35421.26411173527,
    "float": 0.0
  },
  {
    "name": "Sui",
    "symbol": "SUI",
    "gas_symbol": "SUI",
    "gov_symbol": "SUI",
    "category": "L1",
    "is_testnet": false,
    "price": 1.42,
    "change": -0.30237,
    "fdv": 14165399199,
    "mcap": 5293420375,
    "tvl": 1200000000,
    "tx": 1023383,
    "fees": 26913.341918098948,
    "float": 0.3736866360514349
  },
  {
    "name": "Hyperliquid",
    "symbol": "HYPE",
    "gas_symbol": "USDC",
    "gov_symbol": "HYPE",
    "category": "L1",
    "is_testnet": false,
    "price": 138.0,
    "change": -0.42,
    "fdv": 13800000000,
    "mcap": 4500000000,
    "tvl": 900000000,
    "tx": 1159934,
    "fees": 27913.923247004943,
    "float": 0.32608695652173914
  },
  {
    "name": "Monad",
    "symbol": "MON",
    "gas_symbol": "MON",
    "gov_symbol": "MON",
    "category": "L1",
    "is_testnet": false,
    "price": 18.5,
    "change": 0.33,
    "fdv": 18500000000,
    "mcap": 2700000000,
    "tvl": 850000000,
    "tx": 32244659,
    "fees": 1091046.786209972,
    "float": 0.14594594594594595
  },
  {
    "name": "Aptos",
    "symbol": "APT",
    "gas_symbol": "APT",
    "gov_symbol": "APT",
    "category": "L1",
    "is_testnet": false,
    "price": 1.65,
    "change": 3.26526,
    "fdv": 1964441871,
    "mcap": 1237704825,
    "tvl": 550000000,
    "tx": 1126215,
    "fees": 7271.115467066226,
    "float": 0.6300541865206456
  },
  {
    "name": "Berachain",
    "symbol": "BERA",
    "gas_symbol": "BERA",
    "gov_symbol": "BGT",
    "category": "L1",
    "is_testnet": true,
    "price": 0,
    "change": 0,
    "fdv": 2500000000,
    "mcap": 0,
    "tvl": 450000000,
    "tx": 1146923,
    "fees": 48500.53620930561,
    "float": 0.0
  },
  {
    "name": "Sei",
    "symbol": "SEI",
    "gas_symbol": "SEI",
    "gov_symbol": "SEI",
    "category": "L1",
    "is_testnet": false,
    "price": 0.110819,
    "change": 1.06875,
    "fdv": 1107236770,
    "mcap": 718719690,
    "tvl": 220000000,
    "tx": 1058242,
    "fees": 42850.31868149165,
    "float": 0.6491111110769922
  }
]