[
  {
    "name": "Ethereum",
    "symbol": "ETH",
    "gas_symbol": "ETH",
    "gov_symbol": "ETH",
    "category": "L1",
    "is_testnet": false,
    "price": 2053.13,
    "change": -0.73198,
    "fdv": 247816666209,
    "mcap": 247816666209,
    "tvl": 58000000000,
    "tx": 1121537,
    "fees": 35709.193427938684,
    "float": 1.0
  },
  {
    "name": "Arbitrum",
    "symbol": "ARB",
    "gas_symbol": "ETH",
    "gov_symbol": "ARB",
    "category": "L2",
    "is_testnet": false,
    "price": 0.092585,
    "change": 1.39067,
    "fdv": 925823888,
    "mcap": 559273930,
    "tvl": 16000000000,
    "tx": 957742,
    "fees": 16965.242656862967,
    "float": 0.604082414862037
  },
  {
    "name": "Solana",
    "symbol": "SOL",
    "gas_symbol": "SOL",
    "gov_symbol": "SOL",
    "category": "L1",
    "is_testnet": false,
    "price": 80.23,
    "change": 1.32978,
    "fdv": 45949596737,
    "mcap": 45949596173,
    "tvl": 6500000000,
    "tx": 29530354,
    "fees": 438883.3981727441,
    "float": 0.9999999877256812
  },
  {
    "name": "Base",
    "symbol": "ETH",
    "gas_symbol": "ETH",
    "gov_symbol": null,
    "category": "L2",
    "is_testnet": false,
    "price": 1.15e-06,
    "change": 2.7629,
    "fdv": 939638,
    "mcap": 0.0,
    "tvl": 2500000000,
    "tx": 1199642,
    "fees": 20716.524329734188,
    "float": 0.0
  },
  {
    "name": "Sui",
    "symbol": "SUI",
    "gas_symbol": "SUI",
    "gov_symbol": "SUI",
    "category": "L1",
    "is_testnet": false,
    "price": 0.873845,
    "change": 1.17087,
    "fdv": 8739212242,
    "mcap": 3454950495,
    "tvl": 1200000000,
    "tx": 1159770,
    "fees": 30075.16054248757,
    "float": 0.3953388931780105
  },
  {
    "name": "Hyperliquid",
    "symbol": "HYPE",
    "gas_symbol": "USDC",
    "gov_symbol": "HYPE",
    "category": "L1",
    "is_testnet": false,
    "price": 138.0,
    "change": 0.44,
    "fdv": 13800000000,
    "mcap": 4500000000,
    "tvl": 900000000,
    "tx": 1173047,
    "fees": 50080.815104073736,
    "float": 0.32608695652173914
  },
  {
    "name": "Monad",
    "symbol": "MON",
    "gas_symbol": "MON",
    "gov_symbol": "MON",
    "category": "L1",
    "is_testnet": false,
    "price": 18.5,
    "change": -0.59,
    "fdv": 18500000000,
    "mcap": 2700000000,
    "tvl": 850000000,
    "tx": 34386362,
    "fees": 421388.1677151149,
    "float": 0.14594594594594595
  },
  {
    "name": "Aptos",
    "symbol": "APT",
    "gas_symbol": "APT",
    "gov_symbol": "APT",
    "category": "L1",
    "is_testnet": false,
    "price": 0.85106,
    "change": -0.37674,
    "fdv": 1022074610,
    "mcap": 676197481,
    "tvl": 550000000,
    "tx": 828247,
    "fees": 16752.821251570993,
    "float": 0.661593071957829
  },
  {
    "name": "Berachain",
    "symbol": "BERA",
    "gas_symbol": "BERA",
    "gov_symbol": "BGT",
    "category": "L1",
    "is_testnet": true,
    "price": 0,
    "change": 0,
    "fdv": 2500000000,
    "mcap": 0,
    "tvl": 450000000,
    "tx": 868780,
    "fees": 5283.0434852073795,
    "float": 0.0
  },
  {
    "name": "Sei",
    "symbol": "SEI",
    "gas_symbol": "SEI",
    "gov_symbol": "SEI",
    "category": "L1",
    "is_testnet": false,
    "price": 0.054987,
    "change": 6.93732,
    "fdv": 549887894,
    "mcap": 370257849,
    "tvl": 220000000,
    "tx": 1145000,
    "fees": 28934.178735713773,
    "float": 0.6733333340122596
  }
]