[
  {
    "name": "Ethereum",
    "symbol": "ETH",
    "gas_symbol": "ETH",
    "gov_symbol": "ETH",
    "category": "L1",
    "is_testnet": false,
    "price": 2179.97,
    "change": -2.75759,
    "fdv": 263099018826,
    "mcap": 263099018826,
    "tvl": 58000000000,
    "tx": 911822,
    "fees": 43742.910311145446,
    "float": 1.0
  },
  {
    "name": "Arbitrum",
    "symbol": "ARB",
    "gas_symbol": "ETH",
    "gov_symbol": "ARB",
    "category": "L2",
    "is_testnet": false,
    "price": 0.101758,
    "change": 0.0473,
    "fdv": 1017740900,
    "mcap": 614799380,
    "tvl": 16000000000,
    "tx": 805731,
    "fees": 35666.68789576902,
    "float": 0.6040824142962123
  },
  {
    "name": "Solana",
    "symbol": "SOL",
    "gas_symbol": "SOL",
    "gov_symbol": "SOL",
    "category": "L1",
    "is_testnet": false,
    "price": 82.2,
    "change": -2.41737,
    "fdv": 47191547172,
    "mcap": 47191540346,
    "tvl": 6500000000,
    "tx": 35833832,
    "fees": 268190.3967855409,
    "float": 0.9999998553554522
  },
  {
    "name": "Base",
    "symbol": "ETH",
    "gas_symbol": "ETH",
    "gov_symbol": null,
    "category": "L2",
    "is_testnet": false,
    "price": 1.19e-06,
    "change": -7.00294,
    "fdv": 966822,
    "mcap": 0.0,
    "tvl": 2500000000,
    "tx": 806262,
    "fees": 18828.979479590675,
    "float": 0.0
  },
  {
    "name": "Sui",
    "symbol": "SUI",
    "gas_symbol": "SUI",
    "gov_symbol": "SUI",
    "category": "L1",
    "is_testnet": false,
    "price": 0.906677,
    "change": -3.54273,
    "fdv": 9068192944,
    "mcap": 3585009362,
    "tvl": 1200000000,
    "tx": 988175,
    "fees": 25235.833110670937,
    "float": 0.3953388932215027
  },
  {
    "name": "Hyperliquid",
    "symbol": "HYPE",
    "gas_symbol": "USDC",
    "gov_symbol": "HYPE",
    "category": "L1",
    "is_testnet": false,
    "price": 138.0,
    "change": 0.08,
    "fdv": 13800000000,
    "mcap": 4500000000,
    "tvl": 900000000,
    "tx": 1048699,
    "fees": 2972.17331229946,
    "float": 0.32608695652173914
  },
  {
    "name": "Monad",
    "symbol": "MON",
    "gas_symbol": "MON",
    "gov_symbol": "MON",
    "category": "L1",
    "is_testnet": false,
    "price": 18.5,
    "change": 0.29,
    "fdv": 18500000000,
    "mcap": 2700000000,
    "tvl": 850000000,
    "tx": 40413074,
    "fees": 1411234.5116223297,
    "float": 0.14594594594594595
  },
  {
    "name": "Aptos",
    "symbol": "APT",
    "gas_symbol": "APT",
    "gov_symbol": "APT",
    "category": "L1",
    "is_testnet": false,
    "price": 0.824985,
    "change": -4.25092,
    "fdv": 990682213,
    "mcap": 655517270,
    "tvl": 550000000,
    "tx": 856597,
    "fees": 13168.286397646976,
    "float": 0.661682688351648
  },
  {
    "name": "Berachain",
    "symbol": "BERA",
    "gas_symbol": "BERA",
    "gov_symbol": "BGT",
    "category": "L1",
    "is_testnet": true,
    "price": 0,
    "change": 0,
    "fdv": 2500000000,
    "mcap": 0,
    "tvl": 450000000,
    "tx": 886484,
    "fees": 31262.200145034334,
    "float": 0.0
  },
  {
    "name": "Sei",
    "symbol": "SEI",
    "gas_symbol": "SEI",
    "gov_symbol": "SEI",
    "category": "L1",
    "is_testnet": false,
    "price": 0.054697,
    "change": -4.92487,
    "fdv": 547083237,
    "mcap": 368369380,
    "tvl": 220000000,
    "tx": 1123976,
    "fees": 44707.56022477289,
    "float": 0.673333334101041
  }
]