[
  {
    "name": "Ethereum",
    "symbol": "ETH",
    "gas_symbol": "ETH",
    "gov_symbol": "ETH",
    "category": "L1",
    "is_testnet": false,
    "price": 2060.18,
    "change": 2.73417,
    "fdv": 248320078756,
    "mcap": 248320078756,
    "tvl": 58000000000,
    "tx": 917930,
    "fees": 27952.856753181986,
    "float": 1.0
  },
  {
    "name": "Arbitrum",
    "symbol": "ARB",
    "gas_symbol": "ETH",
    "gov_symbol": "ARB",
    "category": "L2",
    "is_testnet": false,
    "price": 0.09268,
    "change": 3.44316,
    "fdv": 926679110,
    "mcap": 559790554,
    "tvl": 16000000000,
    "tx": 1069176,
    "fees": 14551.823273302747,
    "float": 0.6040824142458547
  },
  {
    "name": "Solana",
    "symbol": "SOL",
    "gas_symbol": "SOL",
    "gov_symbol": "SOL",
    "category": "L1",
    "is_testnet": false,
    "price": 84.03,
    "change": 1.92631,
    "fdv": 48074061993,
    "mcap": 48074061443,
    "tvl": 6500000000,
    "tx": 25455945,
    "fees": 1248057.586957622,
    "float": 0.9999999885593192
  },
  {
    "name": "Base",
    "symbol": "ETH",
    "gas_symbol": "ETH",
    "gov_symbol": null,
    "category": "L2",
    "is_testnet": false,
    "price": 1.19e-06,
    "change": 4.51443,
    "fdv": 972143,
    "mcap": 0.0,
    "tvl": 2500000000,
    "tx": 1060323,
    "fees": 3930.4117580732236,
    "float": 0.0
  },
  {
    "name": "Sui",
    "symbol": "SUI",
    "gas_symbol": "SUI",
    "gov_symbol": "SUI",
    "category": "L1",
    "is_testnet": false,
    "price": 0.881749,
    "change": 2.13013,
    "fdv": 8813897780,
    "mcap": 3437406639,
    "tvl": 1200000000,
    "tx": 1169938,
    "fees": 4619.617841344376,
    "float": 0.38999846887264444
  },
  {
    "name": "Hyperliquid",
    "symbol": "HYPE",
    "gas_symbol": "USDC",
    "gov_symbol": "HYPE",
    "category": "L1",
    "is_testnet": false,
    "price": 138.0,
    "change": 1.34,
    "fdv": 13800000000,
    "mcap": 4500000000,
    "tvl": 900000000,
    "tx": 946202,
    "fees": 36754.57756567899,
    "float": 0.32608695652173914
  },
  {
    "name": "Monad",
    "symbol": "MON",
    "gas_symbol": "MON",
    "gov_symbol": "MON",
    "category": "L1",
    "is_testnet": false,
    "price": 18.5,
    "change": -0.59,
    "fdv": 18500000000,
    "mcap": 2700000000,
    "tvl": 850000000,
    "tx": 34682141,
    "fees": 794081.0618350683,
    "float": 0.14594594594594595
  },
  {
    "name": "Aptos",
    "symbol": "APT",
    "gas_symbol": "APT",
    "gov_symbol": "APT",
    "category": "L1",
    "is_testnet": false,
    "price": 0.94418,
    "change": 1.52209,
    "fdv": 1134409646,
    "mcap": 750441553,
    "tvl": 550000000,
    "tx": 1048448,
    "fees": 21657.49553166577,
    "float": 0.6615260683352828
  },
  {
    "name": "Berachain",
    "symbol": "BERA",
    "gas_symbol": "BERA",
    "gov_symbol": "BGT",
    "category": "L1",
    "is_testnet": true,
    "price": 0,
    "change": 0,
    "fdv": 2500000000,
    "mcap": 0,
    "tvl": 450000000,
    "tx": 1108725,
    "fees": 28826.396109760044,
    "float": 0.0
  },
  {
    "name": "Sei",
    "symbol": "SEI",
    "gas_symbol": "SEI",
    "gov_symbol": "SEI",
    "category": "L1",
    "is_testnet": false,
    "price": 0.053629,
    "change": -0.41749,
    "fdv": 536259609,
    "mcap": 361081470,
    "tvl": 220000000,
    "tx": 1096322,
    "fees": 53846.507869439214,
    "float": 0.6733333332214472
  }
]