[
  {
    "name": "Ethereum",
    "symbol": "ETH",
    "gas_symbol": "ETH",
    "gov_symbol": "ETH",
    "category": "L1",
    "is_testnet": false,
    "price": 1938.84,
    "change": -1.49407,
    "fdv": 233918420066,
    "mcap": 233918420066,
    "tvl": 58000000000,
    "tx": 888537,
    "fees": 22141.428110857083,
    "float": 1.0
  },
  {
    "name": "Arbitrum",
    "symbol": "ARB",
    "gas_symbol": "ETH",
    "gov_symbol": "ARB",
    "category": "L2",
    "is_testnet": false,
    "price": 0.095383,
    "change": -0.92546,
    "fdv": 953640765,
    "mcap": 566374398,
    "tvl": 16000000000,
    "tx": 1081754,
    "fees": 6260.778030975884,
    "float": 0.5939074951352358
  },
  {
    "name": "Solana",
    "symbol": "SOL",
    "gas_symbol": "SOL",
    "gov_symbol": "SOL",
    "category": "L1",
    "is_testnet": false,
    "price": 81.8,
    "change": -1.47988,
    "fdv": 50816309377,
    "mcap": 46633352512,
    "tvl": 6500000000,
    "tx": 26196183,
    "fees": 295310.3884127013,
    "float": 0.9176847567979179
  },
  {
    "name": "Base",
    "symbol": "ETH",
    "gas_symbol": "ETH",
    "gov_symbol": null,
    "category": "L2",
    "is_testnet": false,
    "price": 1.27e-06,
    "change": -2.58844,
    "fdv": 1032639,
    "mcap": 0.0,
    "tvl": 2500000000,
    "tx": 823976,
    "fees": 35204.30713841005,
    "float": 0.0
  },
  {
    "name": "Sui",
    "symbol": "SUI",
    "gas_symbol": "SUI",
    "gov_symbol": "SUI",
    "category": "L1",
    "is_testnet": false,
    "price": 0.882003,
    "change": -1.19365,
    "fdv": 8817875190,
    "mcap": 3438957823,
    "tvl": 1200000000,
    "tx": 1015657,
    "fees": 20224.852704475976,
    "float": 0.38999846889418266
  },
  {
    "name": "Hyperliquid",
    "symbol": "HYPE",
    "gas_symbol": "USDC",
    "gov_symbol": "HYPE",
    "category": "L1",
    "is_testnet": false,
    "price": 138.0,
    "change": -0.51,
    "fdv": 13800000000,
    "mcap": 4500000000,
    "tvl": 900000000,
    "tx": 1023337,
    "fees": 22423.353761912305,
    "float": 0.32608695652173914
  },
  {
    "name": "Monad",
    "symbol": "MON",
    "gas_symbol": "MON",
    "gov_symbol": "MON",
    "category": "L1",
    "is_testnet": false,
    "price": 18.5,
    "change": -0.42,
    "fdv": 18500000000,
    "mcap": 2700000000,
    "tvl": 850000000,
    "tx": 34605379,
    "fees": 862166.8580575641,
    "float": 0.14594594594594595
  },
  {
    "name": "Aptos",
    "symbol": "APT",
    "gas_symbol": "APT",
    "gov_symbol": "APT",
    "category": "L1",
    "is_testnet": false,
    "price": 0.929535,
    "change": -0.77521,
    "fdv": 1114200999,
    "mcap": 726054587,
    "tvl": 550000000,
    "tx": 1133928,
    "fees": 37971.04754378085,
    "float": 0.6516369915765979
  },
  {
    "name": "Berachain",
    "symbol": "BERA",
    "gas_symbol": "BERA",
    "gov_symbol": "BGT",
    "category": "L1",
    "is_testnet": true,
    "price": 0,
    "change": 0,
    "fdv": 2500000000,
    "mcap": 0,
    "tvl": 450000000,
    "tx": 853664,
    "fees": 10028.542239418302,
    "float": 0.0
  },
  {
    "name": "Sei",
    "symbol": "SEI",
    "gas_symbol": "SEI",
    "gov_symbol": "SEI",
    "category": "L1",
    "is_testnet": false,
    "price": 0.063064,
    "change": -1.91869,
    "fdv": 630787943,
    "mcap": 424730548,
    "tvl": 220000000,
    "tx": 1183282,
    "fees": 53836.67538196127,
    "float": 0.6733333328788753
  }
]