[
  {
    "name": "Ethereum",
    "symbol": "ETH",
    "gas_symbol": "ETH",
    "gov_symbol": "ETH",
    "category": "L1",
    "is_testnet": false,
    "price": 2398.92,
    "change": 4.41708,
    "fdv": 289541208047,
    "mcap": 289541208047,
    "tvl": 58000000000,
    "tx": 1187969,
    "fees": 17440.782073112197,
    "float": 1.0
  },
  {
    "name": "Arbitrum",
    "symbol": "ARB",
    "gas_symbol": "ETH",
    "gov_symbol": "ARB",
    "category": "L2",
    "is_testnet": false,
    "price": 0.130701,
    "change": 5.69202,
    "fdv": 1305413613,
    "mcap": 788577408,
    "tvl": 16000000000,
    "tx": 834007,
    "fees": 32546.431843441882,
    "float": 0.6040824150651782
  },
  {
    "name": "Solana",
    "symbol": "SOL",
    "gas_symbol": "SOL",
    "gov_symbol": "SOL",
    "category": "L1",
    "is_testnet": false,
    "price": 87.38,
    "change": 3.29105,
    "fdv": 54610644463,
    "mcap": 50302300277,
    "tvl": 6500000000,
    "tx": 31845440,
    "fees": 720471.2779712251,
    "float": 0.9211079776046407
  },
  {
    "name": "Base",
    "symbol": "ETH",
    "gas_symbol": "ETH",
    "gov_symbol": null,
    "category": "L2",
    "is_testnet": false,
    "price": 1.32e-06,
    "change": 5.13245,
    "fdv": 1076610,
    "mcap": 0.0,
    "tvl": 2500000000,
    "tx": 907758,
    "fees": 35010.56053048823,
    "float": 0.0
  },
  {
    "name": "Sui",
    "symbol": "SUI",
    "gas_symbol": "SUI",
    "gov_symbol": "SUI",
    "category": "L1",
    "is_testnet": false,
    "price": 0.957533,
    "change": 3.02276,
    "fdv": 9573316972,
    "mcap": 3784704536,
    "tvl": 1200000000,
    "tx": 1135345,
    "fees": 27767.405137083588,
    "float": 0.39533889320383825
  },
  {
    "name": "Hyperliquid",
    "symbol": "HYPE",
    "gas_symbol": "USDC",
    "gov_symbol": "HYPE",
    "category": "L1",
    "is_testnet": false,
    "price": 138.0,
    "change": 0.28,
    "fdv": 13800000000,
    "mcap": 4500000000,
    "tvl": 900000000,
    "tx": 1185217,
    "fees": 38535.675457473706,
    "float": 0.32608695652173914
  },
  {
    "name": "Monad",
    "symbol": "MON",
    "gas_symbol": "MON",
    "gov_symbol": "MON",
    "category": "L1",
    "is_testnet": false,
    "price": 18.5,
    "change": 0.02,
    "fdv": 18500000000,
    "mcap": 2700000000,
    "tvl": 850000000,
    "tx": 33449778,
    "fees": 1574553.5500721347,
    "float": 0.14594594594594595
  },
  {
    "name": "Aptos",
    "symbol": "APT",
    "gas_symbol": "APT",
    "gov_symbol": "APT",
    "category": "L1",
    "is_testnet": false,
    "price": 0.954895,
    "change": 3.74573,
    "fdv": 1147140383,
    "mcap": 770047923,
    "tvl": 550000000,
    "tx": 833161,
    "fees": 12252.013535928203,
    "float": 0.6712761004770591
  },
  {
    "name": "Berachain",
    "symbol": "BERA",
    "gas_symbol": "BERA",
    "gov_symbol": "BGT",
    "category": "L1",
    "is_testnet": true,
    "price": 0,
    "change": 0,
    "fdv": 2500000000,
    "mcap": 0,
    "tvl": 450000000,
    "tx": 1134665,
    "fees": 22831.539098577003,
    "float": 0.0
  },
  {
    "name": "Sei",
    "symbol": "SEI",
    "gas_symbol": "SEI",
    "gov_symbol": "SEI",
    "category": "L1",
    "is_testnet": false,
    "price": 0.062057,
    "change": 11.10118,
    "fdv": 619745671,
    "mcap": 417295419,
    "tvl": 220000000,
    "tx": 1010661,
    "fees": 42663.52661163742,
    "float": 0.6733333341831443
  }
]