[
  {
    "name": "Ethereum",
    "symbol": "ETH",
    "gas_symbol": "ETH",
    "gov_symbol": "ETH",
    "category": "L1",
    "is_testnet": false,
    "price": 2323.25,
    "change": 0.29603,
    "fdv": 280354204824,
    "mcap": 280354204824,
    "tvl": 58000000000,
    "tx": 1113356,
    "fees": 44987.65392627739,
    "float": 1.0
  },
  {
    "name": "Arbitrum",
    "symbol": "ARB",
    "gas_symbol": "ETH",
    "gov_symbol": "ARB",
    "category": "L2",
    "is_testnet": false,
    "price": 0.14341,
    "change": 0.79852,
    "fdv": 1434044331,
    "mcap": 882040290,
    "tvl": 16000000000,
    "tx": 1032273,
    "fees": 7314.734601488323,
    "float": 0.6150718432706527
  },
  {
    "name": "Solana",
    "symbol": "SOL",
    "gas_symbol": "SOL",
    "gov_symbol": "SOL",
    "category": "L1",
    "is_testnet": false,
    "price": 93.37,
    "change": -0.00602,
    "fdv": 58464555908,
    "mcap": 53933318191,
    "tvl": 6500000000,
    "tx": 25016745,
    "fees": 1175499.126309716,
    "float": 0.9224959867286023
  },
  {
    "name": "Base",
    "symbol": "ETH",
    "gas_symbol": "ETH",
    "gov_symbol": null,
    "category": "L2",
    "is_testnet": false,
    "price": 1.14e-06,
    "change": -5.17678,
    "fdv": 927202,
    "mcap": 0.0,
    "tvl": 2500000000,
    "tx": 1164061,
    "fees": 25726.71016100126,
    "float": 0.0
  },
  {
    "name": "Sui",
    "symbol": "SUI",
    "gas_symbol": "SUI",
    "gov_symbol": "SUI",
    "category": "L1",
    "is_testnet": false,
    "price": 1.12,
    "change": 6.46896,
    "fdv": 11248434463,
    "mcap": 4505468603,
    "tvl": 1200000000,
    "tx": 1029203,
    "fees": 26005.607162814464,
    "float": 0.4005418369836307
  },
  {
    "name": "Hyperliquid",
    "symbol": "HYPE",
    "gas_symbol": "USDC",
    "gov_symbol": "HYPE",
    "category": "L1",
    "is_testnet": false,
    "price": 138.0,
    "change": -1.27,
    "fdv": 13800000000,
    "mcap": 4500000000,
    "tvl": 900000000,
    "tx": 961589,
    "fees": 15185.402459459709,
    "float": 0.32608695652173914
  },
  {
    "name": "Monad",
    "symbol": "MON",
    "gas_symbol": "MON",
    "gov_symbol": "MON",
    "category": "L1",
    "is_testnet": false,
    "price": 18.5,
    "change": -0.87,
    "fdv": 18500000000,
    "mcap": 2700000000,
    "tvl": 850000000,
    "tx": 47605989,
    "fees": 1898027.5525031395,
    "float": 0.14594594594594595
  },
  {
    "name": "Aptos",
    "symbol": "APT",
    "gas_symbol": "APT",
    "gov_symbol": "APT",
    "category": "L1",
    "is_testnet": false,
    "price": 1.11,
    "change": 0.31054,
    "fdv": 1330217949,
    "mcap": 893263005,
    "tvl": 550000000,
    "tx": 894686,
    "fees": 20031.7065108387,
    "float": 0.6715162772172156
  },
  {
    "name": "Berachain",
    "symbol": "BERA",
    "gas_symbol": "BERA",
    "gov_symbol": "BGT",
    "category": "L1",
    "is_testnet": true,
    "price": 0,
    "change": 0,
    "fdv": 2500000000,
    "mcap": 0,
    "tvl": 450000000,
    "tx": 804993,
    "fees": 23625.426438442613,
    "float": 0.0
  },
  {
    "name": "Sei",
    "symbol": "SEI",
    "gas_symbol": "SEI",
    "gov_symbol": "SEI",
    "category": "L1",
    "is_testnet": false,
    "price": 0.068246,
    "change": 2.16424,
    "fdv": 682460269,
    "mcap": 459523248,
    "tvl": 220000000,
    "tx": 818138,
    "fees": 27610.094138484197,
    "float": 0.6733333336361592
  }
]